ecfxa/__init__.py
ecfxa/ecfs.py
ecfxa/erosita.py
ecfxa/singleton.py
ecfxa/swift.py
ecfxa/xmm.py
ecfxa/data/erosita_abscorr_ecfs.json.gz
ecfxa/data/erosita_ecfs.json.gz
ecfxa/data/swift_abscorr_ecfs.json.gz
ecfxa/data/swift_ecfs.json.gz
ecfxa/data/xmm_abscorr_ecfs.json.gz
ecfxa/data/xmm_ecfs.json.gz
ecfxa-1.0.dist-info/LICENSE
ecfxa-1.0.dist-info/METADATA
ecfxa-1.0.dist-info/WHEEL
ecfxa-1.0.dist-info/top_level.txt
ecfxa-1.0.dist-info/RECORD
