Metadata-Version: 2.1
Name: ecfxa
Version: 1.0
Summary: Energy Conversion Factors for X-ray Astronomy
Author-email: Angel Ruiz <angel.ruizca@gmail.com>
Project-URL: Homepage, https://github.com/ruizca/ecfxa
Classifier: Programming Language :: Python :: 3
Classifier: License :: OSI Approved :: BSD License
Classifier: Operating System :: POSIX :: Linux
Classifier: Intended Audience :: Science/Research
Classifier: Topic :: Scientific/Engineering :: Astronomy
Requires-Python: >=3.10
License-File: LICENSE
Requires-Dist: astropy
Requires-Dist: numpy
Requires-Dist: scipy
